redshift_sqlalchemy/__init__.py
sqlalchemy_redshift/__init__.py
sqlalchemy_redshift/commands.py
sqlalchemy_redshift/compat.py
sqlalchemy_redshift/ddl.py
sqlalchemy_redshift/dialect.py
sqlalchemy_redshift/redshift-ca-bundle.crt
openmetadata_sqlalchemy_redshift-0.2.1.dist-info/LICENSE
openmetadata_sqlalchemy_redshift-0.2.1.dist-info/METADATA
openmetadata_sqlalchemy_redshift-0.2.1.dist-info/WHEEL
openmetadata_sqlalchemy_redshift-0.2.1.dist-info/entry_points.txt
openmetadata_sqlalchemy_redshift-0.2.1.dist-info/top_level.txt
openmetadata_sqlalchemy_redshift-0.2.1.dist-info/RECORD
