Metadata-Version: 2.1
Name: openmetadata-sqlalchemy-redshift
Version: 0.2.1
Summary: Amazon Redshift Dialect of sqlalchemy for Openmetadata
Home-page: https://open-metadata.org/
Author: OpenMetadata Committers
License: MIT
Platform: UNKNOWN
Classifier: Development Status :: 4 - Beta
Classifier: Environment :: Console
Classifier: Intended Audience :: Developers
Classifier: License :: OSI Approved :: MIT License
Classifier: Operating System :: OS Independent
Classifier: Programming Language :: Python
Classifier: Programming Language :: Python :: 2
Classifier: Programming Language :: Python :: 2.7
Classifier: Programming Language :: Python :: 3
Classifier: Programming Language :: Python :: 3.4
Classifier: Programming Language :: Python :: 3.5
Classifier: Programming Language :: Python :: 3.6
Classifier: Programming Language :: Python :: 3.7
Requires-Python: >=2.7, !=3.0.*, !=3.1.*, !=3.2.*, !=3.3.*
License-File: LICENSE
Requires-Dist: SQLAlchemy (<2.0.0,>=0.9.2)
Requires-Dist: packaging
Requires-Dist: enum34 (<2.0.0,>=1.1.6) ; python_version < "3.4"
